{
  "78be6ff9": {
    "id": "78be6ff9",
    "timestamp": "2024-10-27T18:59:52.007571",
    "ticker": "AAPL",
    "action": "HOLD",
    "confidence": 85,
    "reasoning": "groq: The stock's RSI indicates a slightly overbought condition, and the low volume, combined with a negative macro score, tempers the bullish outlook from the uptrend candlestick pattern. | cohere: Uptrend with moderate RSI and low volume, but negative macro context suggests caution.",
    "candle_pattern": "swing_highs_lows",
    "indicators": {
      "rsi": 67.13330791269276
    },
    "price_at_prediction": 266.2799987792969,
    "outcome": {
      "checked_date": "2025-10-27T19:18:19.144936",
      "price_at_prediction": 266.2799987792969,
      "price_after": 229.03407287597656,
      "days_held": 2,
      "price_change_pct": -13.99,
      "was_correct": false,
      "action_taken": "HOLD",
      "failure_analysis": "Significant movement (-13.99%) - missed opportunity",
      "test_mode": false
    },
    "was_correct": false
  },
  "2be3d7bf": {
    "id": "2be3d7bf",
    "timestamp": "2024-10-27T18:59:54.018665",
    "ticker": "MSFT",
    "action": "HOLD",
    "confidence": 100,
    "reasoning": "groq: The stock's RSI indicates a slightly overbought condition, and the mixed candlestick patterns, combined with a negative macro score, suggest a cautious approach. | cohere: Mixed technical signals with RSI near overbought territory, low volume, and a negative macro score suggest caution despite potential bullish patterns.",
    "candle_pattern": "double_bottom",
    "indicators": {
      "rsi": 67.93006725430905
    },
    "price_at_prediction": 533.5554809570312,
    "outcome": {
      "checked_date": "2025-10-27T19:18:19.118097",
      "price_at_prediction": 533.5554809570312,
      "price_after": 429.30694580078125,
      "days_held": 2,
      "price_change_pct": -19.54,
      "was_correct": false,
      "action_taken": "HOLD",
      "failure_analysis": "Significant movement (-19.54%) - missed opportunity",
      "test_mode": false
    },
    "was_correct": false
  },
  "e524545b": {
    "id": "e524545b",
    "timestamp": "2024-10-27T18:59:55.932942",
    "ticker": "NVDA",
    "action": "BUY",
    "confidence": 80,
    "reasoning": "groq: The presence of bullish continuation patterns like three_white_soldiers and vcp, along with a relatively neutral RSI, suggests a potential upward trend, despite the negative macro score. | cohere: Mixed technical signals with bullish continuation patterns but low volume and negative macro context suggest caution.",
    "candle_pattern": "three_white_soldiers",
    "indicators": {
      "rsi": 60.89080839779822
    },
    "price_at_prediction": 190.7454071044922,
    "outcome": {
      "checked_date": "2025-10-27T19:18:19.110288",
      "price_at_prediction": 190.7454071044922,
      "price_after": 139.300048828125,
      "days_held": 2,
      "price_change_pct": -26.97,
      "was_correct": false,
      "action_taken": "BUY",
      "failure_analysis": "Market moved against prediction - no clear technical reason",
      "test_mode": false
    },
    "was_correct": false
  },
  "9192971d": {
    "id": "9192971d",
    "timestamp": "2024-10-27T18:59:58.000863",
    "ticker": "TSLA",
    "action": "HOLD",
    "confidence": 100,
    "reasoning": "groq: The stock's RSI indicates a neutral position, and the presence of a consolidation pattern with moderate historical success suggests a wait-and-see approach. | cohere: Mixed technical signals with RSI near neutral, low volume, and uncertain candlestick patterns in a bearish macro context.",
    "candle_pattern": "double_bottom",
    "indicators": {
      "rsi": 59.087995765223035
    },
    "price_at_prediction": 455.25,
    "outcome": {
      "checked_date": "2025-10-27T19:18:19.053695",
      "price_at_prediction": 455.25,
      "price_after": 257.54998779296875,
      "days_held": 2,
      "price_change_pct": -43.43,
      "was_correct": false,
      "action_taken": "HOLD",
      "failure_analysis": "Significant movement (-43.43%) - missed opportunity",
      "test_mode": false
    },
    "was_correct": false
  },
  "fa6adc4a": {
    "id": "fa6adc4a",
    "timestamp": "2024-10-27T19:00:00.311825",
    "ticker": "GOOGL",
    "action": "HOLD",
    "confidence": 80,
    "reasoning": "groq: The stock's high RSI indicates overbought conditions, which tempers the bullish implications of the three_white_soldiers and swing_highs_lows candlestick patterns. | cohere: Overbought RSI (72.92) suggests potential pullback despite bullish candlestick patterns and uptrend, with weak macro context (-14 Macro Score).",
    "candle_pattern": "three_white_soldiers",
    "indicators": {
      "rsi": 72.91994726888207
    },
    "price_at_prediction": 268.75,
    "outcome": {
      "checked_date": "2025-10-27T19:18:19.081575",
      "price_at_prediction": 268.75,
      "price_after": 173.69400024414062,
      "days_held": 2,
      "price_change_pct": -35.37,
      "was_correct": false,
      "action_taken": "HOLD",
      "failure_analysis": "Significant movement (-35.37%) - missed opportunity",
      "test_mode": false
    },
    "was_correct": false
  },
  "45f35a4e": {
    "id": "45f35a4e",
    "timestamp": "2024-10-27T19:00:02.871236",
    "ticker": "TSM",
    "action": "SELL",
    "confidence": 100,
    "reasoning": "groq: The presence of a double_top bearish_reversal pattern with 100% historical success, combined with a negative Macro Score, suggests a strong likelihood of a downward price movement. | cohere: Bearish double-top pattern with 100% historical success and weak market context (Macro Score: -14) outweighs indecision signals.",
    "candle_pattern": "spinning_top",
    "indicators": {
      "rsi": 57.101314696921484
    },
    "price_at_prediction": 297.22491455078125,
    "outcome": {
      "checked_date": "2025-10-27T19:18:19.100518",
      "price_at_prediction": 297.22491455078125,
      "price_after": 192.40843200683594,
      "days_held": 2,
      "price_change_pct": -35.27,
      "was_correct": true,
      "action_taken": "SELL",
      "failure_analysis": "Bearish setup confirmed (-35.27%) | spinning_top pattern worked as expected",
      "test_mode": false
    },
    "was_correct": true
  },
  "b643ebea": {
    "id": "b643ebea",
    "timestamp": "2024-10-27T19:00:04.668141",
    "ticker": "AMD",
    "action": "SELL",
    "confidence": 50,
    "reasoning": "groq: The high RSI value of 74.10 indicates overbought conditions, which, combined with a negative macro score, outweighs the potentially bullish hammer candlestick pattern. | cohere: Overbought RSI (74) and mixed candlestick patterns suggest caution despite bullish signals, especially in a negative macro environment.",
    "candle_pattern": "hammer",
    "indicators": {
      "rsi": 74.09750598361704
    },
    "price_at_prediction": 257.0899963378906,
    "outcome": {
      "checked_date": "2025-10-27T19:18:19.062365",
      "price_at_prediction": 257.0899963378906,
      "price_after": 148.60000610351562,
      "days_held": 2,
      "price_change_pct": -42.2,
      "was_correct": true,
      "action_taken": "SELL",
      "failure_analysis": "Bearish setup confirmed (-42.20%) | hammer pattern worked as expected",
      "test_mode": false
    },
    "was_correct": true
  },
  "e3c96967": {
    "id": "e3c96967",
    "timestamp": "2024-10-27T19:00:07.156153",
    "ticker": "TD.TO",
    "action": "BUY",
    "confidence": 80,
    "reasoning": "groq: The presence of a morning star bullish reversal pattern and an uptrend indication from swing highs and lows suggests a potential buying opportunity, despite low volume and a negative macro score. | cohere: Mixed technical signals with bullish candlestick patterns but low volume and negative macro context suggest caution.",
    "candle_pattern": "morning_star",
    "indicators": {
      "rsi": 67.98589059059579
    },
    "price_at_prediction": 113.94499969482422,
    "outcome": {
      "checked_date": "2025-10-27T19:18:19.165475",
      "price_at_prediction": 113.94499969482422,
      "price_after": 73.88143920898438,
      "days_held": 2,
      "price_change_pct": -35.16,
      "was_correct": false,
      "action_taken": "BUY",
      "failure_analysis": "Morning star failed - context matters (check broader market trend)",
      "test_mode": false
    },
    "was_correct": false
  },
  "ad7f0617": {
    "id": "ad7f0617",
    "timestamp": "2024-10-27T19:00:09.508628",
    "ticker": "UHS",
    "action": "HOLD",
    "confidence": 100,
    "reasoning": "groq: The stock's technical indicators, such as a moderate RSI and mixed candlestick patterns, suggest a neutral outlook, which is further supported by a negative macro score. | cohere: Mixed technical signals with a spinning top indicating indecision, low volume, and a negative macro score suggest caution.",
    "candle_pattern": "spinning_top",
    "indicators": {
      "rsi": 66.77130096561925
    },
    "price_at_prediction": 212.0749969482422,
    "outcome": {
      "checked_date": "2025-10-27T19:18:19.350406",
      "price_at_prediction": 212.0749969482422,
      "price_after": 206.6116485595703,
      "days_held": 2,
      "price_change_pct": -2.58,
      "was_correct": false,
      "action_taken": "HOLD",
      "failure_analysis": "Significant movement (-2.58%) - missed opportunity",
      "test_mode": false
    },
    "was_correct": false
  },
  "1791e93b": {
    "id": "1791e93b",
    "timestamp": "2024-10-27T19:00:12.059261",
    "ticker": "AMZN",
    "action": "HOLD",
    "confidence": 100,
    "reasoning": "groq: The stock's neutral RSI and average volume, combined with mixed candlestick patterns and a negative macro score, suggest a cautious approach, warranting a hold rather than a buy or sell. | cohere: Mixed technical signals with a neutral RSI, low volume, and uncertain candlestick patterns in a negative macro environment.",
    "candle_pattern": "double_bottom",
    "indicators": {
      "rsi": 56.34917979166241
    },
    "price_at_prediction": 226.82139587402344,
    "outcome": {
      "checked_date": "2025-10-27T19:18:19.172623",
      "price_at_prediction": 226.82139587402344,
      "price_after": 192.72999572753906,
      "days_held": 2,
      "price_change_pct": -15.03,
      "was_correct": false,
      "action_taken": "HOLD",
      "failure_analysis": "Significant movement (-15.03%) - missed opportunity",
      "test_mode": false
    },
    "was_correct": false
  },
  "75493f0b": {
    "id": "75493f0b",
    "timestamp": "2024-10-27T19:00:13.946616",
    "ticker": "BTC",
    "action": "HOLD",
    "confidence": 85,
    "reasoning": "groq: The indecision indicated by the spinning top patterns and the low volume suggest a lack of clear direction, making it prudent to hold rather than take a new position.",
    "candle_pattern": "spinning_top",
    "indicators": {
      "rsi": 52.68540881960293
    },
    "price_at_prediction": 51.08000183105469,
    "outcome": {
      "checked_date": "2025-10-27T19:18:19.208125",
      "price_at_prediction": 51.08000183105469,
      "price_after": 31.850000381469727,
      "days_held": 2,
      "price_change_pct": -37.65,
      "was_correct": false,
      "action_taken": "HOLD",
      "failure_analysis": "Significant movement (-37.65%) - missed opportunity",
      "test_mode": false
    },
    "was_correct": false
  },
  "799224bc": {
    "id": "799224bc",
    "timestamp": "2024-10-27T19:00:14.456835",
    "ticker": "ETH",
    "action": "HOLD",
    "confidence": 80,
    "reasoning": "groq: The neutral RSI and average volume, combined with a consolidation candlestick pattern and a negative macro score, suggest a cautious approach, warranting a hold rather than a buy or sell.",
    "candle_pattern": "swing_highs_lows",
    "indicators": {
      "rsi": 52.46930117419945
    },
    "price_at_prediction": 39.720001220703125,
    "outcome": {
      "checked_date": "2025-10-27T19:18:19.245955",
      "price_at_prediction": 39.720001220703125,
      "price_after": 25.0,
      "days_held": 2,
      "price_change_pct": -37.06,
      "was_correct": false,
      "action_taken": "HOLD",
      "failure_analysis": "Significant movement (-37.06%) - missed opportunity",
      "test_mode": false
    },
    "was_correct": false
  },
  "66c35268": {
    "id": "66c35268",
    "timestamp": "2024-10-27T19:00:14.991632",
    "ticker": "SOL",
    "action": "HOLD",
    "confidence": 85,
    "reasoning": "groq: The indecisive spinning top candlestick pattern and moderate RSI value suggest a neutral stance, while the macro score and below-average volume do not strongly support a buy or sell decision.",
    "candle_pattern": "spinning_top",
    "indicators": {
      "rsi": 46.189354411299014
    },
    "price_at_prediction": 1.8450000286102295,
    "outcome": {
      "checked_date": "2025-10-27T19:18:19.253211",
      "price_at_prediction": 1.8450000286102295,
      "price_after": 2.4700000286102295,
      "days_held": 2,
      "price_change_pct": 33.88,
      "was_correct": false,
      "action_taken": "HOLD",
      "failure_analysis": "Significant movement (+33.88%) - missed opportunity",
      "test_mode": false
    },
    "was_correct": false
  },
  "de3f9554": {
    "id": "de3f9554",
    "timestamp": "2025-10-28T09:06:56.441412",
    "ticker": "AAPL",
    "action": "HOLD",
    "confidence": 95,
    "reasoning": "groq: The stock's RSI indicates a slightly overbought condition, and the low volume, combined with a weak macro score, suggests caution, but the uptrend pattern provides some support. | cohere: RSI is near overbought territory (69), volume is below average, and macro conditions are unfavorable (-11 Macro Score).",
    "candle_pattern": "swing_highs_lows",
    "indicators": {
      "rsi": 69.03437276660773
    },
    "price_at_prediction": 268.80999755859375,
    "outcome": null,
    "was_correct": null
  },
  "a46edf9e": {
    "id": "a46edf9e",
    "timestamp": "2025-10-28T09:06:57.943966",
    "ticker": "MSFT",
    "action": "HOLD",
    "confidence": 100,
    "reasoning": "groq: The stock's RSI indicates a slightly overbought condition and the presence of a doji candlestick pattern suggests indecision, warranting a cautious approach. | cohere: Mixed technical signals (RSI near overbought, doji indicating indecision) and negative macro context suggest caution despite potential bullish reversal patterns.",
    "candle_pattern": "doji",
    "indicators": {
      "rsi": 66.5755792767388
    },
    "price_at_prediction": 531.52001953125,
    "outcome": null,
    "was_correct": null
  },
  "d7b5e159": {
    "id": "d7b5e159",
    "timestamp": "2025-10-28T09:06:59.787411",
    "ticker": "NVDA",
    "action": "HOLD",
    "confidence": 100,
    "reasoning": "groq: The stock's neutral RSI and mixed candlestick patterns, combined with a negative macro score, do not provide a strong enough signal to warrant a buy or sell recommendation. | cohere: Mixed technical signals with bullish candlestick patterns but low historical success rates, coupled with a weak macro environment, suggest caution.",
    "candle_pattern": "three_white_soldiers",
    "indicators": {
      "rsi": 61.58984870731723
    },
    "price_at_prediction": 191.49000549316406,
    "outcome": null,
    "was_correct": null
  },
  "7626ed78": {
    "id": "7626ed78",
    "timestamp": "2025-10-28T09:07:02.910030",
    "ticker": "TSLA",
    "action": "HOLD",
    "confidence": 100,
    "reasoning": "groq: The stock's neutral RSI and average volume, combined with the low historical success rates of the candlestick patterns, suggest a cautious approach amidst a negative macro context. | cohere: Mixed signals with RSI indicating neutral momentum, average volume, and conflicting candlestick patterns in a negative macro environment.",
    "candle_pattern": "double_bottom",
    "indicators": {
      "rsi": 58.387946794964485
    },
    "price_at_prediction": 452.4200134277344,
    "outcome": null,
    "was_correct": null
  },
  "c43807b6": {
    "id": "c43807b6",
    "timestamp": "2025-10-28T09:07:04.968667",
    "ticker": "GOOGL",
    "action": "SELL",
    "confidence": 65,
    "reasoning": "groq: The stock's high RSI value of 73.17514096723936 indicates overbought conditions, suggesting a potential reversal, while the bearish macro score of -11 further supports a sell recommendation. | cohere: Overbought RSI (73.175) suggests potential pullback despite bullish candlestick patterns and uptrend, with negative macro context (-11) adding caution.",
    "candle_pattern": "three_white_soldiers",
    "indicators": {
      "rsi": 73.17514096723936
    },
    "price_at_prediction": 269.2699890136719,
    "outcome": null,
    "was_correct": null
  },
  "01973f4d": {
    "id": "01973f4d",
    "timestamp": "2025-10-28T09:07:06.541240",
    "ticker": "TSM",
    "action": "SELL",
    "confidence": 100,
    "reasoning": "groq: The presence of a double_top bearish_reversal pattern with 100% historical success, combined with a negative Macro Score, outweighs the indecision indicated by the doji patterns, suggesting a sell recommendation. | cohere: Bearish double-top pattern with 100% historical success and negative macro context outweighs indecision from doji candles.",
    "candle_pattern": "doji",
    "indicators": {
      "rsi": 57.7033880521923
    },
    "price_at_prediction": 298.25,
    "outcome": null,
    "was_correct": null
  },
  "19b7dfc8": {
    "id": "19b7dfc8",
    "timestamp": "2025-10-28T09:07:08.242750",
    "ticker": "AMD",
    "action": "HOLD",
    "confidence": 35,
    "reasoning": "groq: The appearance of a hammer candlestick pattern, a bullish reversal indicator with 100% historical success, outweighs other factors, suggesting a potential trend reversal. | cohere: Mixed technical signals with high RSI indicating potential overbought conditions, despite bullish candlestick patterns, and a negative macro context.",
    "candle_pattern": "hammer",
    "indicators": {
      "rsi": 74.91962117630744
    },
    "price_at_prediction": 259.6700134277344,
    "outcome": null,
    "was_correct": null
  },
  "57d22240": {
    "id": "57d22240",
    "timestamp": "2025-10-28T09:07:10.188362",
    "ticker": "TD.TO",
    "action": "HOLD",
    "confidence": 100,
    "reasoning": "groq: The presence of a morning star bullish reversal pattern and an uptrend swing highs lows pattern suggests potential for upward movement, but the low volume and negative macro score warrant caution. | cohere: Mixed technical signals with bullish candlestick patterns (Morning Star, Double Bottom) but low historical success rates and weak market context (Macro Score -11) suggest caution.",
    "candle_pattern": "morning_star",
    "indicators": {
      "rsi": 68.93591611938095
    },
    "price_at_prediction": 114.26000213623047,
    "outcome": null,
    "was_correct": null
  },
  "78d159f0": {
    "id": "78d159f0",
    "timestamp": "2025-10-28T09:07:12.230938",
    "ticker": "UHS",
    "action": "HOLD",
    "confidence": 100,
    "reasoning": "groq: The stock's technical indicators, such as a high RSI and bullish continuation pattern, suggest potential for upward movement, but are countered by a downtrend pattern and negative macro score, leading to a cautious hold recommendation. | cohere: Mixed technical signals with bullish continuation and reversal patterns, but downtrend and negative macro context warrant caution.",
    "candle_pattern": "vcp",
    "indicators": {
      "rsi": 68.72230491551818
    },
    "price_at_prediction": 214.02999877929688,
    "outcome": null,
    "was_correct": null
  },
  "d79a996e": {
    "id": "d79a996e",
    "timestamp": "2025-10-28T09:07:14.358097",
    "ticker": "AMZN",
    "action": "HOLD",
    "confidence": 100,
    "reasoning": "groq: The stock's neutral RSI and mixed candlestick patterns, combined with a negative macro score, suggest a cautious approach, warranting a hold rather than a buy or sell. | cohere: Mixed technical signals with RSI in neutral territory, low volume, and uncertain candlestick patterns amid a negative macro environment suggest caution.",
    "candle_pattern": "spinning_top",
    "indicators": {
      "rsi": 56.65498899546437
    },
    "price_at_prediction": 226.97000122070312,
    "outcome": null,
    "was_correct": null
  },
  "6db097e8": {
    "id": "6db097e8",
    "timestamp": "2025-10-28T09:07:15.693148",
    "ticker": "BTC",
    "action": "HOLD",
    "confidence": 85,
    "reasoning": "groq: The indecision candlestick patterns and low volume suggest a lack of clear direction, making it prudent to hold rather than take a new position.",
    "candle_pattern": "spinning_top",
    "indicators": {
      "rsi": 52.12764318961676
    },
    "price_at_prediction": 50.900001525878906,
    "outcome": null,
    "was_correct": null
  },
  "59f35b14": {
    "id": "59f35b14",
    "timestamp": "2025-10-28T09:07:16.134465",
    "ticker": "ETH",
    "action": "HOLD",
    "confidence": 85,
    "reasoning": "groq: The indecision candlestick patterns and moderate RSI value suggest a neutral stance, while the negative macro score and average volume do not provide a strong bullish or bearish signal.",
    "candle_pattern": "spinning_top",
    "indicators": {
      "rsi": 51.94822247084093
    },
    "price_at_prediction": 39.52000045776367,
    "outcome": null,
    "was_correct": null
  },
  "c8fcba97": {
    "id": "c8fcba97",
    "timestamp": "2025-10-28T09:07:16.422035",
    "ticker": "SOL",
    "action": "HOLD",
    "confidence": 80,
    "reasoning": "groq: The neutral RSI and low volume, combined with a consolidation pattern and a negative macro score, suggest a cautious approach, warranting a hold rather than a buy or sell.",
    "candle_pattern": "swing_highs_lows",
    "indicators": {
      "rsi": 45.16541769170795
    },
    "price_at_prediction": 1.840000033378601,
    "outcome": null,
    "was_correct": null
  },
  "00985c3c": {
    "id": "00985c3c",
    "timestamp": "2025-10-28T09:36:01.517433",
    "ticker": "AAPL",
    "action": "HOLD",
    "confidence": 100,
    "reasoning": "groq: The stock's RSI indicates a slightly overbought condition, and the low volume, combined with a weak macro score, suggests caution despite a potentially bullish candlestick pattern. | cohere: RSI is nearing overbought territory (69) and volume is below average, suggesting caution despite the uptrend signal.",
    "candle_pattern": "swing_highs_lows",
    "indicators": {
      "rsi": 69.03437276736427
    },
    "price_at_prediction": 268.80999755859375,
    "outcome": null,
    "was_correct": null
  },
  "644c9b76": {
    "id": "644c9b76",
    "timestamp": "2025-10-28T09:36:03.525522",
    "ticker": "MSFT",
    "action": "HOLD",
    "confidence": 100,
    "reasoning": "groq: The stock's technical indicators, such as a high RSI and low volume, suggest a potential pullback, while the market context's negative macro score further supports a cautious approach. | cohere: Mixed technical signals with RSI near overbought territory and uncertain candlestick patterns, coupled with a negative macro score, suggest caution.",
    "candle_pattern": "doji",
    "indicators": {
      "rsi": 66.57557927794312
    },
    "price_at_prediction": 531.52001953125,
    "outcome": null,
    "was_correct": null
  },
  "812acf59": {
    "id": "812acf59",
    "timestamp": "2025-10-28T09:36:05.490960",
    "ticker": "NVDA",
    "action": "HOLD",
    "confidence": 100,
    "reasoning": "groq: The stock's technical indicators, such as a moderate RSI and low volume, combined with mixed candlestick patterns and a negative macro score, suggest a neutral outlook. | cohere: Mixed technical signals with bullish candlestick patterns but low historical success rates, coupled with a negative macro score, suggest caution.",
    "candle_pattern": "three_white_soldiers",
    "indicators": {
      "rsi": 61.58984870732292
    },
    "price_at_prediction": 191.49000549316406,
    "outcome": null,
    "was_correct": null
  },
  "0f44475c": {
    "id": "0f44475c",
    "timestamp": "2025-10-28T09:36:07.581188",
    "ticker": "TSLA",
    "action": "HOLD",
    "confidence": 100,
    "reasoning": "groq: The stock's neutral RSI and average volume, combined with a bearish macro score, suggest a cautious approach, outweighing the potentially bullish double bottom pattern. | cohere: Mixed technical signals with a neutral RSI, average volume, and uncertain candlestick patterns, coupled with a negative macro score, suggest caution.",
    "candle_pattern": "double_bottom",
    "indicators": {
      "rsi": 58.387946794964485
    },
    "price_at_prediction": 452.4200134277344,
    "outcome": null,
    "was_correct": null
  },
  "925c615a": {
    "id": "925c615a",
    "timestamp": "2025-10-28T09:36:09.011285",
    "ticker": "GOOGL",
    "action": "SELL",
    "confidence": 75,
    "reasoning": "groq: The stock's high RSI value of 73.18 indicates overbought conditions, suggesting a potential reversal, especially considering the bearish macro context with a Macro Score of -10. | cohere: Overbought RSI (73.175) and mixed candlestick patterns with low historical success rates suggest caution despite uptrend signals.",
    "candle_pattern": "three_white_soldiers",
    "indicators": {
      "rsi": 73.17514096716468
    },
    "price_at_prediction": 269.2699890136719,
    "outcome": null,
    "was_correct": null
  },
  "467b5098": {
    "id": "467b5098",
    "timestamp": "2025-10-28T09:36:10.596838",
    "ticker": "TSM",
    "action": "SELL",
    "confidence": 100,
    "reasoning": "groq: The presence of a double_top bearish_reversal pattern with 100% historical success, combined with a negative Macro Score, outweighs the indecision indicated by the doji patterns, suggesting a bearish outlook. | cohere: Bearish double top pattern with 100% historical success and negative macro context outweighs indecision from doji patterns.",
    "candle_pattern": "doji",
    "indicators": {
      "rsi": 57.7033880521346
    },
    "price_at_prediction": 298.25,
    "outcome": null,
    "was_correct": null
  },
  "9db55666": {
    "id": "9db55666",
    "timestamp": "2025-10-28T09:36:12.051833",
    "ticker": "AMD",
    "action": "BUY",
    "confidence": 45,
    "reasoning": "groq: The appearance of a hammer candlestick pattern, a bullish reversal indicator with 100% historical success, outweighs other factors, suggesting a potential upside for AMD. | cohere: Mixed technical signals with a high RSI indicating potential overbought conditions, despite bullish candlestick patterns, and a negative macro score.",
    "candle_pattern": "hammer",
    "indicators": {
      "rsi": 74.91962117630744
    },
    "price_at_prediction": 259.6700134277344,
    "outcome": null,
    "was_correct": null
  },
  "e5ea8d6d": {
    "id": "e5ea8d6d",
    "timestamp": "2025-10-28T09:36:14.194568",
    "ticker": "TD.TO",
    "action": "BUY",
    "confidence": 100,
    "reasoning": "groq: The presence of a morning star candlestick pattern, a bullish reversal indicator with 40% historical success, outweighs the negative macro score and suggests a potential buying opportunity. | cohere: Mixed technical signals with bullish candlestick patterns but low historical success rates and weak market context.",
    "candle_pattern": "morning_star",
    "indicators": {
      "rsi": 68.93591612000253
    },
    "price_at_prediction": 114.26000213623047,
    "outcome": null,
    "was_correct": null
  },
  "d747be41": {
    "id": "d747be41",
    "timestamp": "2025-10-28T09:36:15.782415",
    "ticker": "UHS",
    "action": "HOLD",
    "confidence": 100,
    "reasoning": "groq: The stock's technical indicators, such as a high RSI and bullish continuation pattern, suggest potential for upward movement, but are countered by a downtrend pattern and negative macro score, leading to a cautious hold recommendation. | cohere: Mixed technical signals with bullish continuation and reversal patterns, but a negative macro score and downtrend suggest caution.",
    "candle_pattern": "vcp",
    "indicators": {
      "rsi": 68.72230491559972
    },
    "price_at_prediction": 214.02999877929688,
    "outcome": null,
    "was_correct": null
  },
  "1170da7f": {
    "id": "1170da7f",
    "timestamp": "2025-10-28T09:36:17.534488",
    "ticker": "AMZN",
    "action": "HOLD",
    "confidence": 100,
    "reasoning": "groq: The stock's neutral RSI and mixed candlestick patterns, combined with a negative macro score, suggest a cautious approach, warranting a hold rather than a buy or sell. | cohere: Mixed technical signals (RSI neutral, low volume, indecisive candlestick patterns) and negative macro context suggest caution.",
    "candle_pattern": "spinning_top",
    "indicators": {
      "rsi": 56.65498899546437
    },
    "price_at_prediction": 226.97000122070312,
    "outcome": null,
    "was_correct": null
  },
  "13ed1465": {
    "id": "13ed1465",
    "timestamp": "2025-10-28T09:36:19.282670",
    "ticker": "BTC",
    "action": "HOLD",
    "confidence": 95,
    "reasoning": "groq: The neutral RSI and indecisive candlestick patterns, combined with below-average volume, suggest a lack of clear direction, making a hold position the most prudent choice.",
    "candle_pattern": "spinning_top",
    "indicators": {
      "rsi": 52.12764318961676
    },
    "price_at_prediction": 50.900001525878906,
    "outcome": null,
    "was_correct": null
  },
  "5324e4f3": {
    "id": "5324e4f3",
    "timestamp": "2025-10-28T09:36:19.799237",
    "ticker": "ETH",
    "action": "HOLD",
    "confidence": 95,
    "reasoning": "groq: The indecision patterns and consolidation signals, combined with a neutral RSI and slightly above-average volume, suggest a wait-and-see approach for ETH.",
    "candle_pattern": "spinning_top",
    "indicators": {
      "rsi": 51.94822247084093
    },
    "price_at_prediction": 39.52000045776367,
    "outcome": null,
    "was_correct": null
  },
  "2f4c7858": {
    "id": "2f4c7858",
    "timestamp": "2025-10-28T09:36:20.215983",
    "ticker": "SOL",
    "action": "HOLD",
    "confidence": 90,
    "reasoning": "groq: The neutral RSI and low volume, combined with a relatively low-success candlestick pattern and negative macro score, suggest a cautious approach, warranting a hold rather than a buy or sell.",
    "candle_pattern": "swing_highs_lows",
    "indicators": {
      "rsi": 45.16541769170795
    },
    "price_at_prediction": 1.840000033378601,
    "outcome": null,
    "was_correct": null
  },
  "b45ba01e": {
    "id": "b45ba01e",
    "timestamp": "2025-10-28T19:37:16.271084",
    "ticker": "AAPL",
    "action": "HOLD",
    "confidence": 100,
    "reasoning": "cohere: Technical indicators show indecision with low volume and mixed patterns, while macro conditions are unfavorable, suggesting a cautious approach.",
    "candle_pattern": {
      "name": "spinning_top",
      "type": "indecision",
      "strength": "weak",
      "description": "Spinning Top - indecision"
    },
    "indicators": {
      "rsi": 69.1170451103854,
      "volume_ratio": 0.5464833641006497,
      "macro_score": -4.174375
    },
    "price_at_prediction": 268.8999938964844,
    "outcome": null,
    "was_correct": null
  },
  "898dab75": {
    "id": "898dab75",
    "timestamp": "2025-10-28T19:37:17.443263",
    "ticker": "MSFT",
    "action": "HOLD",
    "confidence": 100,
    "reasoning": "cohere: Overbought RSI (74.0) and mixed technical patterns (low success rates) alongside negative macro conditions suggest caution despite potential bullish reversal signals.",
    "candle_pattern": {
      "name": "double_bottom",
      "type": "bullish_reversal",
      "strength": "strong",
      "description": "W-shape bullish reversal pattern",
      "enhanced": true,
      "strength_score": 85
    },
    "indicators": {
      "rsi": 74.04613480308133,
      "volume_ratio": 1.0940401743029111,
      "macro_score": -4.174375
    },
    "price_at_prediction": 543.9400024414062,
    "outcome": null,
    "was_correct": null
  },
  "a8509ad4": {
    "id": "a8509ad4",
    "timestamp": "2025-10-28T19:37:18.668849",
    "ticker": "NVDA",
    "action": "HOLD",
    "confidence": 100,
    "reasoning": "cohere: Overbought RSI (70.4) and mixed pattern success rates suggest caution despite bullish continuation signals.",
    "candle_pattern": {
      "name": "three_white_soldiers",
      "type": "bullish_continuation",
      "strength": "strong",
      "description": "Three White Soldiers - strong uptrend"
    },
    "indicators": {
      "rsi": 70.44210875540838,
      "volume_ratio": 1.1011197863318916,
      "macro_score": -4.174375
    },
    "price_at_prediction": 202.64999389648438,
    "outcome": null,
    "was_correct": null
  },
  "c632640b": {
    "id": "c632640b",
    "timestamp": "2025-10-28T19:37:19.723588",
    "ticker": "TSLA",
    "action": "HOLD",
    "confidence": 100,
    "reasoning": "cohere: Mixed technical signals with moderate RSI, low volume, and uncertain pattern success rates, coupled with a negative macro score, suggest caution.",
    "candle_pattern": {
      "name": "double_bottom",
      "type": "bullish_reversal",
      "strength": "strong",
      "description": "W-shape bullish reversal pattern",
      "enhanced": true,
      "strength_score": 85
    },
    "indicators": {
      "rsi": 61.037131193405486,
      "volume_ratio": 0.7197468272159577,
      "macro_score": -4.174375
    },
    "price_at_prediction": 462.0498962402344,
    "outcome": null,
    "was_correct": null
  },
  "47f441ca": {
    "id": "47f441ca",
    "timestamp": "2025-10-28T19:37:20.918375",
    "ticker": "GOOGL",
    "action": "HOLD",
    "confidence": 90,
    "reasoning": "cohere: Overbought RSI (70.7) and weak macro conditions (-4) offset the uptrend pattern, suggesting caution despite moderate technicals (50/100).",
    "candle_pattern": {
      "name": "swing_highs_lows",
      "type": "uptrend",
      "strength": "strong",
      "description": "Price action showing uptrend",
      "enhanced": true,
      "strength_score": 75
    },
    "indicators": {
      "rsi": 70.7167532608982,
      "volume_ratio": 0.6345004809556207,
      "macro_score": -4.174375
    },
    "price_at_prediction": 267.70001220703125,
    "outcome": null,
    "was_correct": null
  },
  "1e33826d": {
    "id": "1e33826d",
    "timestamp": "2025-10-28T19:37:22.415635",
    "ticker": "TSM",
    "action": "HOLD",
    "confidence": 100,
    "reasoning": "cohere: Mixed technical signals with moderate RSI, low volume, and conflicting pattern success rates, coupled with a negative macro score, suggest caution.",
    "candle_pattern": {
      "name": "morning_star",
      "type": "bullish_reversal",
      "strength": "very_strong",
      "description": "Morning Star - major reversal signal"
    },
    "indicators": {
      "rsi": 59.635231257428906,
      "volume_ratio": 0.6638678943550669,
      "macro_score": -4.174375
    },
    "price_at_prediction": 301.927490234375,
    "outcome": null,
    "was_correct": null
  },
  "157f65cc": {
    "id": "157f65cc",
    "timestamp": "2025-10-28T19:37:23.515295",
    "ticker": "AMD",
    "action": "HOLD",
    "confidence": 80,
    "reasoning": "cohere: Overbought RSI (75.0) and mixed indecision patterns suggest caution despite bullish continuation signals, with weak macro conditions (-4) adding uncertainty.",
    "candle_pattern": {
      "name": "three_white_soldiers",
      "type": "bullish_continuation",
      "strength": "strong",
      "description": "Three White Soldiers - strong uptrend"
    },
    "indicators": {
      "rsi": 75.01743602260905,
      "volume_ratio": 0.8713425033003047,
      "macro_score": -4.174375
    },
    "price_at_prediction": 259.93798828125,
    "outcome": null,
    "was_correct": null
  },
  "5726ff8a": {
    "id": "5726ff8a",
    "timestamp": "2025-10-28T19:37:24.624161",
    "ticker": "TD.TO",
    "action": "HOLD",
    "confidence": 90,
    "reasoning": "cohere: Mixed technical signals with overbought RSI and low pattern success rates, coupled with negative macro conditions, suggest caution.",
    "candle_pattern": {
      "name": "three_white_soldiers",
      "type": "bullish_continuation",
      "strength": "strong",
      "description": "Three White Soldiers - strong uptrend"
    },
    "indicators": {
      "rsi": 71.67977665340342,
      "volume_ratio": 0.321380771146478,
      "macro_score": -4.174375
    },
    "price_at_prediction": 115.2249984741211,
    "outcome": null,
    "was_correct": null
  },
  "836e9866": {
    "id": "836e9866",
    "timestamp": "2025-10-28T19:37:25.872329",
    "ticker": "UHS",
    "action": "HOLD",
    "confidence": 100,
    "reasoning": "cohere: Overbought RSI and mixed technical patterns with a negative macro score suggest caution, but high volume indicates potential momentum.",
    "candle_pattern": {
      "name": "doji",
      "type": "indecision",
      "strength": "weak",
      "description": "Doji - market indecision"
    },
    "indicators": {
      "rsi": 72.81870514537101,
      "volume_ratio": 1.4089655164012955,
      "macro_score": -4.174375
    },
    "price_at_prediction": 218.6300048828125,
    "outcome": null,
    "was_correct": null
  },
  "dc45d8d7": {
    "id": "dc45d8d7",
    "timestamp": "2025-10-28T19:37:27.151086",
    "ticker": "AMZN",
    "action": "HOLD",
    "confidence": 100,
    "reasoning": "cohere: Mixed technical signals (neutral RSI, low volume, and uncertain pattern success) combined with a negative macro score suggest caution until clearer trends emerge.",
    "candle_pattern": {
      "name": "double_bottom",
      "type": "bullish_reversal",
      "strength": "strong",
      "description": "W-shape bullish reversal pattern",
      "enhanced": true,
      "strength_score": 85
    },
    "indicators": {
      "rsi": 59.67693261367819,
      "volume_ratio": 0.8720734318683521,
      "macro_score": -4.174375
    },
    "price_at_prediction": 229.91000366210938,
    "outcome": null,
    "was_correct": null
  },
  "6b27768e": {
    "id": "6b27768e",
    "timestamp": "2025-10-28T19:37:27.457215",
    "ticker": "BTC",
    "action": "BUY",
    "confidence": 60,
    "reasoning": "Rule-based decision",
    "candle_pattern": {
      "name": "swing_highs_lows",
      "type": "consolidation",
      "strength": "strong",
      "description": "Price action showing consolidation",
      "enhanced": true,
      "strength_score": 60
    },
    "indicators": {
      "rsi": 50.55865842380113,
      "volume_ratio": 0.6737641697925929,
      "macro_score": -4.174375
    },
    "price_at_prediction": 50.47999954223633,
    "outcome": null,
    "was_correct": null
  },
  "1e29b6f1": {
    "id": "1e29b6f1",
    "timestamp": "2025-10-28T19:37:27.834813",
    "ticker": "ETH",
    "action": "BUY",
    "confidence": 75,
    "reasoning": "Rule-based decision",
    "candle_pattern": {
      "name": "swing_highs_lows",
      "type": "uptrend",
      "strength": "strong",
      "description": "Price action showing uptrend",
      "enhanced": true,
      "strength_score": 75
    },
    "indicators": {
      "rsi": 48.51096071989552,
      "volume_ratio": 1.0428743879605369,
      "macro_score": -4.174375
    },
    "price_at_prediction": 38.31999969482422,
    "outcome": null,
    "was_correct": null
  },
  "e0ed01f0": {
    "id": "e0ed01f0",
    "timestamp": "2025-10-28T19:37:28.156850",
    "ticker": "SOL",
    "action": "BUY",
    "confidence": 75,
    "reasoning": "Rule-based decision",
    "candle_pattern": {
      "name": "bullish_engulfing",
      "type": "bullish_reversal",
      "strength": "strong",
      "description": "Bullish Engulfing - strong reversal signal"
    },
    "indicators": {
      "rsi": 47.711954208681384,
      "volume_ratio": 0.48767763428011635,
      "macro_score": -4.174375
    },
    "price_at_prediction": 1.8502000570297241,
    "outcome": null,
    "was_correct": null
  },
  "00fd419b": {
    "id": "00fd419b",
    "timestamp": "2025-10-28T20:18:10.886788",
    "ticker": "AAPL",
    "action": "HOLD",
    "confidence": 100,
    "reasoning": "groq: The stock's RSI indicates a slightly overbought condition, and the mixed candlestick patterns, combined with a negative macro score, suggest a cautious approach. | cohere: Mixed technical signals with RSI nearing overbought territory and low macro score suggest caution despite bullish candlestick patterns.",
    "candle_pattern": "three_white_soldiers",
    "indicators": {
      "rsi": 69.17687507871405
    },
    "price_at_prediction": 269.0,
    "outcome": null,
    "was_correct": null
  },
  "d6dd96a6": {
    "id": "d6dd96a6",
    "timestamp": "2025-10-28T20:18:12.081562",
    "ticker": "MSFT",
    "action": "SELL",
    "confidence": 85,
    "reasoning": "groq: The stock's high RSI value of 73.09 indicates overbought conditions, suggesting a potential reversal, and the negative Macro Score of -4 further supports a bearish outlook. | cohere: Overbought RSI (73) and mixed candlestick patterns with low historical success rates suggest caution despite high volume, while negative macro context adds uncertainty.",
    "candle_pattern": "double_bottom",
    "indicators": {
      "rsi": 73.09592837098093
    },
    "price_at_prediction": 542.0700073242188,
    "outcome": null,
    "was_correct": null
  },
  "3fbc947f": {
    "id": "3fbc947f",
    "timestamp": "2025-10-28T20:18:13.102745",
    "ticker": "NVDA",
    "action": "SELL",
    "confidence": 100,
    "reasoning": "groq: The stock's high RSI value and lack of historical success in current candlestick patterns, combined with a negative Macro Score, suggest a potential downturn. | cohere: Mixed technical signals with bullish patterns but low historical success rates, coupled with a negative macro score, suggest caution.",
    "candle_pattern": "three_white_soldiers",
    "indicators": {
      "rsi": 69.4162348169426
    },
    "price_at_prediction": 201.02999877929688,
    "outcome": null,
    "was_correct": null
  },
  "54f3102c": {
    "id": "54f3102c",
    "timestamp": "2025-10-28T20:18:14.034960",
    "ticker": "TSLA",
    "action": "HOLD",
    "confidence": 100,
    "reasoning": "groq: The stock's RSI indicates a neutral position, and the lack of strong candlestick patterns, combined with a low macro score, suggests a cautious approach. | cohere: Mixed technical signals with RSI near neutral, low volume, and uncertain candlestick patterns in a negative macro environment.",
    "candle_pattern": "double_bottom",
    "indicators": {
      "rsi": 60.6295994249553
    },
    "price_at_prediction": 460.54998779296875,
    "outcome": null,
    "was_correct": null
  },
  "c9aab50c": {
    "id": "c9aab50c",
    "timestamp": "2025-10-28T20:18:14.894298",
    "ticker": "GOOGL",
    "action": "SELL",
    "confidence": 75,
    "reasoning": "groq: The stock's high RSI value of 70.44 indicates overbought conditions, suggesting a potential reversal, especially considering the negative Macro Score. | cohere: Overbought RSI (70.44) and weak macro context (-4) suggest caution despite uptrend signals.",
    "candle_pattern": "swing_highs_lows",
    "indicators": {
      "rsi": 70.43748093130208
    },
    "price_at_prediction": 267.4700012207031,
    "outcome": null,
    "was_correct": null
  },
  "d43df7fa": {
    "id": "d43df7fa",
    "timestamp": "2025-10-28T20:18:15.840000",
    "ticker": "TSM",
    "action": "HOLD",
    "confidence": 100,
    "reasoning": "groq: The presence of a morning star candlestick pattern, a bullish reversal indicator with 40% historical success, suggests a potential uptrend, but the low volume and negative macro score warrant caution. | cohere: Mixed technical signals with bullish reversal patterns (morning star, double bottom) but low historical success rates and weak market context (Macro Score: -4) suggest caution.",
    "candle_pattern": "morning_star",
    "indicators": {
      "rsi": 59.48730404803615
    },
    "price_at_prediction": 301.5299987792969,
    "outcome": null,
    "was_correct": null
  },
  "b7c74f73": {
    "id": "b7c74f73",
    "timestamp": "2025-10-28T20:18:16.881686",
    "ticker": "AMD",
    "action": "SELL",
    "confidence": 45,
    "reasoning": "groq: The bearish shooting star candlestick pattern and high RSI value of 73.63 suggest a potential reversal, outweighing the bullish inverted hammer pattern in the current weak macro context. | cohere: Mixed technical signals with RSI indicating overbought conditions and conflicting candlestick patterns, coupled with a negative macro score, suggest caution.",
    "candle_pattern": "inverted_hammer",
    "indicators": {
      "rsi": 73.62627829862751
    },
    "price_at_prediction": 258.010009765625,
    "outcome": null,
    "was_correct": null
  },
  "4a1759af": {
    "id": "4a1759af",
    "timestamp": "2025-10-28T20:18:17.850042",
    "ticker": "TD.TO",
    "action": "SELL",
    "confidence": 85,
    "reasoning": "groq: The high RSI value of 71.87 indicates overbought conditions, suggesting a potential reversal, and the low historical success rates of the identified candlestick patterns further support a bearish outlook. | cohere: Overbought RSI (71.87) and mixed candlestick patterns with low historical success rates suggest caution despite volume strength.",
    "candle_pattern": "three_white_soldiers",
    "indicators": {
      "rsi": 71.87488900326731
    },
    "price_at_prediction": 115.29000091552734,
    "outcome": null,
    "was_correct": null
  },
  "02041028": {
    "id": "02041028",
    "timestamp": "2025-10-28T20:18:19.028145",
    "ticker": "UHS",
    "action": "SELL",
    "confidence": 95,
    "reasoning": "groq: The high RSI value and bearish candlestick patterns, combined with a negative Macro Score, indicate a potential downtrend, suggesting a sell recommendation. | cohere: Overbought RSI (73.34) and mixed candlestick patterns (doji, double bottom, downtrend) suggest caution despite high volume, while negative macro context (-4) adds uncertainty.",
    "candle_pattern": "doji",
    "indicators": {
      "rsi": 73.34240306482458
    },
    "price_at_prediction": 219.32000732421875,
    "outcome": null,
    "was_correct": null
  },
  "5924bfe4": {
    "id": "5924bfe4",
    "timestamp": "2025-10-28T20:18:19.924775",
    "ticker": "AMZN",
    "action": "HOLD",
    "confidence": 100,
    "reasoning": "groq: The stock's neutral RSI and mixed candlestick patterns, including a spinning top and double bottom, suggest indecision and uncertainty, warranting a cautious hold stance. | cohere: Mixed technical signals (RSI near neutral, indecision pattern) and negative macro context suggest caution.",
    "candle_pattern": "spinning_top",
    "indicators": {
      "rsi": 59.00557713685211
    },
    "price_at_prediction": 229.25,
    "outcome": null,
    "was_correct": null
  },
  "d1e090ba": {
    "id": "d1e090ba",
    "timestamp": "2025-10-28T20:18:20.445533",
    "ticker": "BTC",
    "action": "HOLD",
    "confidence": 90,
    "reasoning": "groq: The neutral RSI and low volume, combined with a consolidation pattern and a negative macro score, suggest a cautious approach, neither strongly favoring a buy or sell.",
    "candle_pattern": "swing_highs_lows",
    "indicators": {
      "rsi": 50.04515626905012
    },
    "price_at_prediction": 50.310001373291016,
    "outcome": null,
    "was_correct": null
  },
  "dd0a1a61": {
    "id": "dd0a1a61",
    "timestamp": "2025-10-28T20:18:21.049267",
    "ticker": "ETH",
    "action": "HOLD",
    "confidence": 100,
    "reasoning": "groq: The neutral RSI and average volume, combined with a relatively low-success candlestick pattern and negative macro score, suggest a cautious approach, warranting a hold rather than a buy or sell.",
    "candle_pattern": "swing_highs_lows",
    "indicators": {
      "rsi": 47.82628508484909
    },
    "price_at_prediction": 38.060001373291016,
    "outcome": null,
    "was_correct": null
  },
  "882c49a5": {
    "id": "882c49a5",
    "timestamp": "2025-10-28T20:18:21.611814",
    "ticker": "SOL",
    "action": "BUY",
    "confidence": 100,
    "reasoning": "groq: The presence of multiple bullish candlestick patterns, including piercing_line, bullish_marubozu, and tweezer_bottom, suggests a potential reversal, outweighing the neutral RSI and low volume.",
    "candle_pattern": "piercing_line",
    "indicators": {
      "rsi": 47.66428988776056
    },
    "price_at_prediction": 1.850000023841858,
    "outcome": null,
    "was_correct": null
  },
  "42a3afd7": {
    "id": "42a3afd7",
    "timestamp": "2025-10-29T04:45:30.327638",
    "ticker": "AAPL",
    "action": "HOLD",
    "confidence": 100,
    "reasoning": "groq: The stock's RSI indicates a slightly overbought condition, and the mixed candlestick patterns, including a bullish continuation and indecision patterns, suggest a pause in the uptrend. | cohere: Mixed technical signals with RSI nearing overbought territory and low historical success rates for candlestick patterns, balanced by an uptrend and neutral market context.",
    "candle_pattern": "three_white_soldiers",
    "indicators": {
      "rsi": 69.17687507946327
    },
    "price_at_prediction": 269.0,
    "outcome": null,
    "was_correct": null
  },
  "a9a7be50": {
    "id": "a9a7be50",
    "timestamp": "2025-10-29T04:45:32.256509",
    "ticker": "MSFT",
    "action": "SELL",
    "confidence": 85,
    "reasoning": "groq: The high RSI value of 73 indicates overbought conditions, suggesting a potential reversal, and the low Macro Score of 1 implies unfavorable market context. | cohere: Overbought RSI (73) suggests potential pullback despite bullish candlestick patterns and high volume, with weak macro context (Macro Score: 1) limiting upside momentum.",
    "candle_pattern": "double_bottom",
    "indicators": {
      "rsi": 73.0959283721874
    },
    "price_at_prediction": 542.0700073242188,
    "outcome": null,
    "was_correct": null
  },
  "5d540246": {
    "id": "5d540246",
    "timestamp": "2025-10-29T04:45:33.936797",
    "ticker": "NVDA",
    "action": "SELL",
    "confidence": 100,
    "reasoning": "groq: The high RSI value of 69.42 indicates overbought conditions, suggesting a potential reversal, and the low historical success rates of the bullish candlestick patterns do not provide strong support for a continued upward trend. | cohere: Mixed technical signals with bullish patterns but low historical success rates and a neutral macro score suggest caution.",
    "candle_pattern": "three_white_soldiers",
    "indicators": {
      "rsi": 69.4162348169109
    },
    "price_at_prediction": 201.02999877929688,
    "outcome": null,
    "was_correct": null
  },
  "32751848": {
    "id": "32751848",
    "timestamp": "2025-10-29T04:45:35.522125",
    "ticker": "TSLA",
    "action": "HOLD",
    "confidence": 100,
    "reasoning": "groq: The stock's RSI indicates a neutral position, and the low historical success rates of the candlestick patterns, combined with a low macro score, suggest a cautious approach. | cohere: Mixed technical signals with RSI near neutral, low volume, and uncertain candlestick patterns in a weak market context.",
    "candle_pattern": "double_bottom",
    "indicators": {
      "rsi": 60.6295994249553
    },
    "price_at_prediction": 460.54998779296875,
    "outcome": null,
    "was_correct": null
  },
  "174aaba2": {
    "id": "174aaba2",
    "timestamp": "2025-10-29T04:45:37.146752",
    "ticker": "GOOGL",
    "action": "SELL",
    "confidence": 75,
    "reasoning": "groq: The stock's high RSI value of 70.44 indicates overbought conditions, suggesting a potential reversal, despite the presence of a bullish uptrend candlestick pattern. | cohere: Overbought RSI (70.44) suggests potential pullback despite uptrend, and low macro score (1) indicates uncertain market conditions.",
    "candle_pattern": "swing_highs_lows",
    "indicators": {
      "rsi": 70.43748093142415
    },
    "price_at_prediction": 267.4700012207031,
    "outcome": null,
    "was_correct": null
  },
  "1168b3ae": {
    "id": "1168b3ae",
    "timestamp": "2025-10-29T04:45:38.152247",
    "ticker": "TSM",
    "action": "BUY",
    "confidence": 100,
    "reasoning": "groq: The presence of a morning star candlestick pattern, a bullish reversal indicator with 40% historical success, suggests a potential upside movement. | cohere: Mixed technical signals with bullish candlestick patterns but low historical success rates and neutral RSI, alongside a weak macro context, suggest caution.",
    "candle_pattern": "morning_star",
    "indicators": {
      "rsi": 59.48730404803608
    },
    "price_at_prediction": 301.5299987792969,
    "outcome": null,
    "was_correct": null
  },
  "be8977ba": {
    "id": "be8977ba",
    "timestamp": "2025-10-29T04:45:38.982246",
    "ticker": "AMD",
    "action": "SELL",
    "confidence": 50,
    "reasoning": "groq: The high RSI value and presence of bearish reversal patterns, such as the shooting star, suggest a potential downturn in AMD's stock price. | cohere: Mixed candlestick patterns and overbought RSI suggest uncertainty, while average volume and low macro score indicate caution.",
    "candle_pattern": "inverted_hammer",
    "indicators": {
      "rsi": 73.62627829862751
    },
    "price_at_prediction": 258.010009765625,
    "outcome": null,
    "was_correct": null
  },
  "48663782": {
    "id": "48663782",
    "timestamp": "2025-10-29T04:45:39.810125",
    "ticker": "TD.TO",
    "action": "SELL",
    "confidence": 85,
    "reasoning": "groq: The high RSI value of 71.87 indicates overbought conditions, suggesting a potential reversal, and the low historical success rates of the identified candlestick patterns further support a bearish outlook. | cohere: Overbought RSI (71.87) suggests potential pullback despite bullish candlestick patterns and above-average volume.",
    "candle_pattern": "three_white_soldiers",
    "indicators": {
      "rsi": 71.87488898778626
    },
    "price_at_prediction": 115.29000091552734,
    "outcome": null,
    "was_correct": null
  },
  "2eca5fb6": {
    "id": "2eca5fb6",
    "timestamp": "2025-10-29T04:45:40.893627",
    "ticker": "UHS",
    "action": "SELL",
    "confidence": 95,
    "reasoning": "groq: The high RSI value of 73.34 indicates overbought conditions, and the presence of a downtrend pattern, combined with a low Macro Score of 1, suggests a potential reversal, making it a favorable time to sell. | cohere: Overbought RSI (73.34) and mixed candlestick patterns (doji and double bottom) suggest caution despite high volume, with a weak macro context (Macro Score: 1).",
    "candle_pattern": "doji",
    "indicators": {
      "rsi": 73.34240306123408
    },
    "price_at_prediction": 219.32000732421875,
    "outcome": null,
    "was_correct": null
  },
  "889977f3": {
    "id": "889977f3",
    "timestamp": "2025-10-29T04:45:41.768323",
    "ticker": "AMZN",
    "action": "HOLD",
    "confidence": 100,
    "reasoning": "groq: The stock's neutral RSI and mixed candlestick patterns, including a spinning top indicating indecision, suggest a hold position until a clearer trend emerges. | cohere: Mixed technical signals with RSI near neutral, average volume, and indecisive candlestick patterns in a weak market context suggest caution.",
    "candle_pattern": "spinning_top",
    "indicators": {
      "rsi": 59.00557713685211
    },
    "price_at_prediction": 229.25,
    "outcome": null,
    "was_correct": null
  },
  "27252f8d": {
    "id": "27252f8d",
    "timestamp": "2025-10-29T04:45:42.207686",
    "ticker": "BTC",
    "action": "HOLD",
    "confidence": 90,
    "reasoning": "groq: The neutral RSI and low volume, combined with a candlestick pattern having only 25% historical success, suggest a cautious approach, warranting a hold rather than a buy or sell.",
    "candle_pattern": "swing_highs_lows",
    "indicators": {
      "rsi": 50.04515626905012
    },
    "price_at_prediction": 50.310001373291016,
    "outcome": null,
    "was_correct": null
  },
  "3d7c2408": {
    "id": "3d7c2408",
    "timestamp": "2025-10-29T04:45:42.646393",
    "ticker": "ETH",
    "action": "HOLD",
    "confidence": 100,
    "reasoning": "groq: The neutral RSI and average volume, combined with a relatively low macro score, suggest a cautious approach, while the uptrend candlestick pattern provides some bullish indication.",
    "candle_pattern": "swing_highs_lows",
    "indicators": {
      "rsi": 47.82628508484909
    },
    "price_at_prediction": 38.060001373291016,
    "outcome": null,
    "was_correct": null
  },
  "2382dd37": {
    "id": "2382dd37",
    "timestamp": "2025-10-29T04:45:43.136917",
    "ticker": "SOL",
    "action": "BUY",
    "confidence": 90,
    "reasoning": "groq: The presence of a piercing_line candlestick pattern, a bullish reversal indicator with 50% historical success, suggests a potential upward trend, warranting a buy recommendation.",
    "candle_pattern": "piercing_line",
    "indicators": {
      "rsi": 47.66428988776056
    },
    "price_at_prediction": 1.850000023841858,
    "outcome": null,
    "was_correct": null
  }
}